CHANGES.txt
TODO.txt
bootstrap.py
buildout.cfg
setup.py
src/lovely/__init__.py
src/lovely.remotetask.egg-info/PKG-INFO
src/lovely.remotetask.egg-info/SOURCES.txt
src/lovely.remotetask.egg-info/dependency_links.txt
src/lovely.remotetask.egg-info/namespace_packages.txt
src/lovely.remotetask.egg-info/not-zip-safe
src/lovely.remotetask.egg-info/requires.txt
src/lovely.remotetask.egg-info/top_level.txt
src/lovely/remotetask/DEPENDENCIES.cfg
src/lovely/remotetask/README.txt
src/lovely/remotetask/SETUP.cfg
src/lovely/remotetask/TESTING.txt
src/lovely/remotetask/__init__.py
src/lovely/remotetask/configure.zcml
src/lovely/remotetask/ftesting.zcml
src/lovely/remotetask/ftests.py
src/lovely/remotetask/interfaces.py
src/lovely/remotetask/job.py
src/lovely/remotetask/lovely.remotetask-configure.zcml
src/lovely/remotetask/processor.py
src/lovely/remotetask/processor.txt
src/lovely/remotetask/service.py
src/lovely/remotetask/startlater.txt
src/lovely/remotetask/task.py
src/lovely/remotetask/testing.py
src/lovely/remotetask/tests.py
src/lovely/remotetask/xmlrpc.py
src/lovely/remotetask/xmlrpc.txt
src/lovely/remotetask/xmlrpc.zcml
src/lovely/remotetask/browser/README.txt
src/lovely/remotetask/browser/__init__.py
src/lovely/remotetask/browser/configure.zcml
src/lovely/remotetask/browser/cronjob.pt
src/lovely/remotetask/browser/job.py
src/lovely/remotetask/browser/jobs.pt
src/lovely/remotetask/browser/service.py
src/lovely/remotetask/browser/table_header.pt
src/lovely/remotetask/browser/icons/ascending.gif
src/lovely/remotetask/browser/icons/decending.gif
src/lovely/remotetask/generations/__init__.py
src/lovely/remotetask/generations/configure.zcml