Metadata-Version: 1.0
Name: lovely.remotetask
Version: 0.5.1
Summary: A remotetask client utiltiy for zope 3
Home-page: http://pypi.python.org/pypi/lovely.remotetask
Author: Lovely Systems
Author-email: office@lovelysystems.com
License: ZPL 2.1
Keywords: zope3 zope remotetask cache ram
Platform: UNKNOWN
